odoo/addons/account_global_discount/README.rst
odoo/addons/account_global_discount/__init__.py
odoo/addons/account_global_discount/__manifest__.py
odoo/addons/account_global_discount/i18n/.empty
odoo/addons/account_global_discount/i18n/account_global_discount.pot
odoo/addons/account_global_discount/i18n/es.po
odoo/addons/account_global_discount/i18n/it.po
odoo/addons/account_global_discount/i18n/pt.po
odoo/addons/account_global_discount/migrations/12.0.2.0.0/post-migration.py
odoo/addons/account_global_discount/models/__init__.py
odoo/addons/account_global_discount/models/account_invoice.py
odoo/addons/account_global_discount/models/account_move_line.py
odoo/addons/account_global_discount/models/global_discount.py
odoo/addons/account_global_discount/readme/CONTRIBUTORS.rst
odoo/addons/account_global_discount/readme/DESCRIPTION.rst
odoo/addons/account_global_discount/readme/ROADMAP.rst
odoo/addons/account_global_discount/readme/USAGE.rst
odoo/addons/account_global_discount/security/ir.model.access.csv
odoo/addons/account_global_discount/security/security.xml
odoo/addons/account_global_discount/static/description/icon.png
odoo/addons/account_global_discount/static/description/icon.svg
odoo/addons/account_global_discount/static/description/index.html
odoo/addons/account_global_discount/tests/__init__.py
odoo/addons/account_global_discount/tests/test_global_discount.py
odoo/addons/account_global_discount/views/account_invoice_views.xml
odoo/addons/account_global_discount/views/global_discount_views.xml
odoo/addons/account_global_discount/views/report_account_invoice.xml
odoo12_addon_account_global_discount-12.0.1.2.2.dist-info/METADATA
odoo12_addon_account_global_discount-12.0.1.2.2.dist-info/WHEEL
odoo12_addon_account_global_discount-12.0.1.2.2.dist-info/top_level.txt
odoo12_addon_account_global_discount-12.0.1.2.2.dist-info/RECORD
